{
  "1": "cmbjreeep02vljo0jlu3l1isp",
  "2": "cmbjregxw02vwjo0jm9q4ks9n",
  "3": "cmbjrejcx02w7jo0jph5alra4",
  "4": "cmbjrelpp02wijo0jzo6ycnrd",
  "5": "cmbjreo4d02wtjo0jugzu2r33",
  "6": "cmbjreqh302x4jo0j79dqdz8n",
  "7": "cmbjresv102xfjo0jnedcf5rp",
  "8": "cmbjreva402xqjo0j9g1x8gc8",
  "9": "cmbjrexku02y1jo0jjh1ut1ss",
  "10": "cmbjrezy402ycjo0jf10d4lmf",
  "11": "cmbjkx9f202rvikij47ch6x24",
  "12": "cmbjrf2fy02ynjo0jof43h1py",
  "13": "cmbjrf4mh02ywjo0js1t83syv",
  "14": "cmbjrf6zm02z3jo0jndmbkh67",
  "15": "cmbjrf95u02zajo0j7c84nk9x",
  "16": "cmbjrfbdo02zhjo0jx4vgsxtl",
  "17": "cmbjrfdjy02zojo0j7ggyokgs",
  "18": "cmbjrffrs02zvjo0ji7javhmu",
  "19": "cmbjrfhy70302jo0j8je1nw3m",
  "20": "cmbjrfk4u0309jo0j7ti1k1rq",
  "21": "cmbjks99m01ulikijhqojfxj8",
  "22": "cmbjrfma9030gjo0j9l2be1f1",
  "23": "cmbjrfogv030njo0jahmyt675",
  "24": "cmbjrfqpu030ujo0j2pa8fvwz",
  "25": "cmbjrfswj0311jo0jew5z0tov",
  "26": "cmbjrfv2q0318jo0jgiiwh3d5",
  "27": "cmbjrfx9w031fjo0jirtphuib",
  "28": "cmbjrfzfc031mjo0j0bgftd1n",
  "29": "cmbjrg1m3031tjo0jzia61awh",
  "30": "cmbjrg3ro0320jo0jgdxg1eyi",
  "31": "cmbjrg5yp0327jo0jdge89eqh",
  "32": "cmbjrg843032ejo0jb0ytpu1h",
  "33": "cmbjrgaam032ljo0jwue5g1vn",
  "34": "cmbjktjyf022sikijgtvretvc",
  "35": "cmbjrgcfv032sjo0j33yqbkza",
  "36": "cmbjrgem7032zjo0jj4l5gie2",
  "37": "cmbjrggve0336jo0j493iu20c",
  "38": "cmbjrgj3b033djo0jc0tmj70o",
  "39": "cmbjrgl9y033kjo0juxal34dy",
  "40": "cmbjrgnfv033rjo0jow9ufua1",
  "41": "cmbjrgpp6033yjo0jap2qhy45",
  "42": "cmbjrgryp0345jo0jl8c598j3",
  "43": "cmbjrgu3j034cjo0j8rj7eyfo",
  "44": "cmbjrgw79034jjo0j1ciwu07c",
  "45": "cmbjrgyd5034ojo0jais4wmj9",
  "46": "cmbjrh0iw034vjo0jsu0vpeqm",
  "47": "cmbjrh2pw0352jo0j3p93786m",
  "48": "cmbjrh4vg0359jo0jeldm8m55",
  "49": "cmbjrh6z7035gjo0jd0tbxxx8",
  "50": "cmbjrh948035njo0j6shstz01",
  "51": "cmbjrhba6035ujo0jxpyrzhgt",
  "52": "cmbjrhdmi0361jo0jmznc0we7",
  "53": "cmbjrhfqx0368jo0j3l325asg",
  "54": "cmbjrhhvw036fjo0jdeqc8gty",
  "55": "cmbjrhk1x036mjo0jwbazhs3d",
  "56": "cmbjrhm79036tjo0jtk5idmcw",
  "57": "cmbjrhoby0370jo0jss7w1tcb",
  "58": "cmbjrhqi20377jo0jotul281t",
  "59": "cmbjrhsq5037ejo0j17msdgjq",
  "60": "cmbjrhuue037ljo0jo2ayu2kh",
  "61": "cmbjrhx8g037sjo0jx9kpyvi4",
  "62": "cmbjrhzfd037zjo0j7i5r3xkm",
  "63": "cmbjkrusk01rwikijd1zu41kh",
  "64": "cmbjri1lh0386jo0jwq7pmefc",
  "65": "cmbjksr4h01y2ikijtp26hewb",
  "66": "cmbjkq28101fuikij4epyt8we",
  "67": "cmbjri3rc038djo0jues1zeyl",
  "68": "cmbjri5xy038kjo0j172ji683",
  "69": "cmbjri8b2038rjo0jngasm0jr",
  "70": "cmbjriaby038ujo0jtbn6kvyj",
  "71": "cmbjktyyt025eikijx0f7venv",
  "72": "cmbjricgw038xjo0jnngaevqa",
  "73": "cmbjriehq0390jo0j1divd1j0",
  "74": "cmbjrigjc0393jo0jlrd2m7de",
  "75": "cmbjriihz0396jo0jbdzo7cm9",
  "76": "cmbjrikk50399jo0jhz980h9v",
  "77": "cmbjrimkq039cjo0je153pcnt",
  "78": "cmbjrioku039fjo0jsts2j78n",
  "79": "cmbjriqo2039ijo0jdqd57o2m",
  "80": "cmbjks32401tfikij3i0vcb38",
  "81": "cmbjrisme039ljo0jr07aq3uc",
  "82": "cmbjriulm039ojo0jl9nuetlm",
  "83": "cmbjriwi4039rjo0jueqnfc20",
  "84": "cmbjriyg9039ujo0jyjo32zd2",
  "85": "cmbjrj0dx039xjo0j6jgsvuhy",
  "86": "cmbjrj2e003a0jo0jlhgzcokg",
  "87": "cmbjkornp0170ikijesybh6tj",
  "88": "cmbjrj4cb03a3jo0jk5odacqk",
  "89": "cmbjrj5ca03a4jo0jifs0yp5c",
  "90": "cmbjrj7a403a7jo0j0apnhe0p",
  "91": "cmbjrj98j03aajo0jnxkko33k",
  "92": "cmbjplzqq0000n3q0qpyxgh2f",
  "93": "cmbjrjd7503afjo0jyxe4xssg",
  "94": "cmbjrjf7g03aijo0j8oeyegb7",
  "95": "cmbjrjha003aljo0jt2ktm3kb",
  "96": "cmbjrjjdq03aojo0jecs0geck",
  "97": "cmbjrjlcy03arjo0jzv4ye8ww",
  "98": "cmbjrjncb03aujo0jgef53au8",
  "99": "cmbjrjpao03axjo0jawsj4xu5",
  "100": "cmbjrjreg03b0jo0jwithszpx",
  "101": "cmbjrjtes03b3jo0j6n9pwna0",
  "102": "cmbjrjvf503b6jo0je24gs0qr",
  "103": "cmbjrjxir03b9jo0je39nwhy4",
  "104": "cmbjrjzgc03bcjo0jlb9pb202",
  "105": "cmbjrk1o303bfjo0jjutkpfll",
  "106": "cmbjrk3lh03bijo0jgalgh0k4",
  "107": "cmbjrk5l303bljo0j1miji0ll",
  "108": "cmbjrk7jv03bojo0j9l8s9o98",
  "109": "cmbjrk9jg03brjo0jl26y9sdf",
  "110": "cmbjrkbhj03bujo0jvkpji7zg",
  "111": "cmbjrkdgv03bxjo0jo2sczxva",
  "112": "cmbjrkfnl03c0jo0jsw5x20mg",
  "113": "cmbjrkhl203c3jo0jyyu58c9g",
  "114": "cmbjrkjj303c6jo0j69okz03u",
  "115": "cmbjrklhc03c9jo0jws2ee4xt",
  "116": "cmbjkp1qu018yikij3xg4u6k1",
  "117": "cmbjkqjh901j2ikijtmedf46f",
  "118": "cmbjkteiy021yikijin5c5dlf",
  "119": "cmbjrknp103ccjo0js739z1ql",
  "120": "cmbjrkpoj03cfjo0j8w4pklm3",
  "121": "cmbjkucyq028dikijgx79hh44",
  "122": "cmbjrkrmi03cijo0ju2bqew5u",
  "123": "cmbjrktjw03cljo0jdj5u4c92",
  "124": "cmbjrkvhf03cojo0jxry5bew7",
  "125": "cmbjrkxin03crjo0ji2411ujg",
  "126": "cmbjkukor02a4ikijta3zmj54",
  "127": "cmbjkuodv02avikijoghbzjyf",
  "128": "cmbjksmzv01x4ikijdxz32mkq",
  "129": "cmbjkuze802d7ikij2s26crxb",
  "130": "cmbjkrib301pcikijn11paqs6",
  "131": "cmbjksv9t01yqikijmeugu7kn",
  "132": "cmbjkpb2601awikij4wwdl7jn",
  "133": "cmbjku6ik026yikijs7y9fs97",
  "134": "cmbjkrkb901pnikijxpeqigf3",
  "135": "cmbjrkzfp03cujo0jakzekgba",
  "136": "cmbjkqax601hfikijct6wgai3",
  "137": "cmbjrl1dk03cxjo0jederinju",
  "138": "cmbjrl3ao03d0jo0jjilvzp5l",
  "139": "cmbjkxxei02u9ikij6zpalfkn",
  "140": "cmbjkqlt301jhikij2sux1ozi",
  "141": "cmbjky2hg02uqikijwz2b8ejo",
  "142": "cmbjr9rhw02ddjo0juigbmrpm",
  "143": "cmbjksx0x01ywikij5qnldypt",
  "144": "cmbjkrbm801o4ikijoy0z5hvc",
  "145": "cmbjkpwbq01erikijlre52j4k",
  "146": "cmbjkq44p01g5ikij7bouhovv",
  "147": "cmbjksrfg01y3ikijip7nn339",
  "148": "cmbjkswjn01ytikijfikwj8w4",
  "149": "cmbjkol48015wikijiwtp444c",
  "150": "cmbjkv4it02e9ikijfebyhhce",
  "151": "cmbjkrkoq01ptikijwi7asz32",
  "152": "cmbjqi74i01i1jo0jcvft7fdr",
  "153": "cmbjrl5x703d3jo0jg1tjj3ca",
  "154": "cmbjksqxr01y0ikijg98kspwu",
  "155": "cmbjrl7tj03d6jo0jho4nwdtl",
  "156": "cmbjksa1g01uuikijvgutbb7n",
  "157": "cmbjkqoco01jxikij673lnvav",
  "158": "cmbjkoo9u016likij5uoxne8q",
  "159": "cmbjksek801vmikijldz8mhzd",
  "160": "cmbjks3q201tnikijgkhtjg4s",
  "161": "cmbjkod9x014gikijyb4428pz",
  "162": "cmbjkovd7017rikijt25i964u",
  "163": "cmbjkof4z014sikijyjqg9l05",
  "164": "cmbjkq8e601gyikij1asbfftq",
  "165": "cmbjku5ty026rikijcdksszhp",
  "166": "cmbjkt5m7020eikijzmho5twu",
  "167": "cmbjkpxp201ewikijc9g34yto",
  "168": "cmbjrl8xi03d7jo0jybkkukmo",
  "169": "cmbjkst0j01y8ikij1f1hrqfi",
  "170": "cmbjkod61014fikijl3ovbiz7",
  "171": "cmbjr34ai01x9jo0jekc9ws4h",
  "172": "cmbjkr2tf01mkikij0zjwynqa",
  "173": "cmbjktbsy021iikij0ts37o08",
  "174": "cmbjktfuv0224ikijvpjmj0ir",
  "175": "cmbjkoktk015sikijrgppl7r1",
  "176": "cmbjqnzy001qljo0jadfcamte",
  "177": "cmbjrasj802i7jo0jcszklp5p",
  "178": "cmbjkp9vq01alikijz81bfeo1",
  "179": "cmbjkq4fs01gaikijhx3ptk1v",
  "180": "cmbjqkzp201ocjo0jckbfh0lw",
  "181": "cmbjkvf7p02gjikijffdt0te2",
  "182": "cmbjkpheu01c3ikijvamvcgcs",
  "183": "cmbjkpmx201d3ikijybd36sgu",
  "184": "cmbjkpfw701buikijobvqhn7m",
  "185": "cmbjkoawe013yikijel05gbva",
  "186": "cmbjku9jy027jikiji6r01xka",
  "187": "cmbjrlazf03dajo0jxsl23kiq",
  "188": "cmbjkvd5502g5ikijurcp1ahg",
  "189": "cmbjksupo01yjikijyzsvwnmy",
  "190": "cmbjkolix0163ikijjt38lelz",
  "191": "cmbjkrnj901qcikij9xfwuf5o",
  "192": "cmbjkphxk01cbikijt7m1lobx",
  "193": "cmbjkx51102raikijdn24t8vc",
  "194": "cmbjkppdx01dhikij0sjqi0aj",
  "195": "cmbjkrqyw01qyikij585602sq",
  "196": "cmbjkrt3o01rhikijg4xken9v",
  "197": "cmbjktnw4023iikijk4qj3tpb",
  "198": "cmbjkwjw102nwikijmwwcqo2r",
  "199": "cmbjkr2ee01miikijfs5vjth2",
  "200": "cmbjkqu4m01kxikij5ijyawgh",
  "201": "cmbjkpoym01dcikijs2j295in",
  "202": "cmbjkprz401dzikijsc8it82s",
  "203": "cmbjkts9d0249ikijcjvg8dt3",
  "204": "cmbjkpcik01b3ikijm2vgecc5",
  "205": "cmbjqslu301rojo0j1ftt6ng1",
  "206": "cmbjkum8t02agikijqz590f27",
  "207": "cmbjkwljq02o6ikij9cokaegq",
  "208": "cmbjkssc401y4ikijwx3j914n",
  "209": "cmbjku599026oikijhp62imc0",
  "210": "cmbjkqzuc01m3ikije9qfeeur",
  "211": "cmbjkruoz01rvikijv0nzbks1",
  "212": "cmbjpv01z0001jo0jgmqsf7eo",
  "213": "cmbjkw8vc02m2ikijiizeaj45",
  "214": "cmbjkra4801nxikijq4dh8c8t",
  "215": "cmbjkoubz017jikijb9q2ya2v",
  "216": "cmbjkrz9c01svikijd5lf73c0",
  "217": "cmbjkqbba01hiikijrs2ttzy3",
  "218": "cmbjkqk1o01j7ikijynvohynt",
  "219": "cmbjkpv2y01efikijy695wt5q",
  "220": "cmbjkp7wp01a7ikij7qbljyv1",
  "221": "cmbjkozr4018likijcz8p9q7j",
  "222": "cmbjquvkt01s4jo0jo3mz5s16",
  "223": "cmbjkqx1g01llikijrv9scodf",
  "224": "cmbjkp6qm01a0ikijh7wh7oyu",
  "225": "cmbjkoq63016vikijhmmkmj9s",
  "226": "cmbjr5aw0020qjo0jh3okudfo",
  "227": "cmbjkw81002lvikijundcx749",
  "228": "cmbjkvbfb02fsikijnq0x1zni",
  "229": "cmbjkubnz0283ikij833wdf77",
  "230": "cmbjkx1k002quikijwccwkjes",
  "231": "cmbjkrc0d01oaikijtdm78vjl",
  "232": "cmbjkv5y402ekikijydehhy2t",
  "233": "cmbjkp49o019likijzc1os9go",
  "234": "cmbjkpeun01bjikij3tnm4cax",
  "235": "cmbjkoj1z015fikijhrem5kp6",
  "236": "cmbjkr17r01mdikijzahwc7c9",
  "237": "cmbjn1azz000fzvzut35j1mh3",
  "238": "cmbjn1adf0009zvzuosshwnzl",
  "239": "cmbjkpya501f3ikijgt58kf1j",
  "240": "cmbjqhvnp01h4jo0jlt8m95u2",
  "241": "cmbjkt3dt01zzikijrr2fbwmx"
}